{
  "Blog": {
    "2021_03_21": [
      {
        "Path": "Categories/Blog/2021_03_21/1_Procrastination.html",
        "FileName": "1_Procrastination.html",
        "Date": "Blog",
        "Title": "Handling our emotions",
        "Tags": "Emotion, Cognitive, Behaviour",
        "Synopsis": "Ways to categorize our reactions to daily life in three distinct categories; Fight, Flight or Freeze"
      }
    ]
  },
  "Investment": {
    "2021_02_28": [
      {
        "Path": "Categories/Investment/2021_02_28/1_RotationOfFunds.html",
        "FileName": "1_RotationOfFunds.html",
        "Date": "Investment",
        "Title": "Notes on the rotation of funds 2021.",
        "Tags": "Stocks, Market Movement, 2021",
        "Synopsis": "A compilation of sources from sites like Reddit regarding the changes that the market has just experienced during Feb 2021"
      }
    ]
  },
  "Language": {
    "2021_2_17": [
      {
        "Path": "Categories/Language/2021_2_17/1_HelloWorld.html",
        "FileName": "1_HelloWorld.html",
        "Date": "Language",
        "Title": "Hello World",
        "Tags": "TEST,ABC,123",
        "Synopsis": "Hello World First Post"
      }
    ]
  },
  "Linux": {
    "2021_1_31": [
      {
        "Path": "Categories/Linux/2021_1_31/1_HelloWorld.html",
        "FileName": "1_HelloWorld.html",
        "Date": "Linux",
        "Title": "Hello World",
        "Tags": "TEST,ABC,123",
        "Synopsis": "Hello World First Post"
      }
    ]
  },
  "Readings": {
    "2021_1_31": [
      {
        "Path": "Categories/Readings/2021_1_31/1_HelloWorld.html",
        "FileName": "1_HelloWorld.html",
        "Date": "Readings",
        "Title": "Hello World",
        "Tags": "TEST,ABC,123",
        "Synopsis": "Hello World First Post"
      }
    ]
  }
}
